almpy/__init__.py
almpy/almpy.py
almpy-0.1.0.dist-info/LICENSE
almpy-0.1.0.dist-info/METADATA
almpy-0.1.0.dist-info/WHEEL
almpy-0.1.0.dist-info/top_level.txt
almpy-0.1.0.dist-info/RECORD
